jiraX/__init__.py
jiraX/backlog.py
jiraX/base.py
jiraX/board.py
jiraX/comment.py
jiraX/factories.py
jiraX/issue.py
jiraX/project.py
jiraX/role.py
jiraX/sprint.py
jiraX/sprintbacklog.py
jiraX/user.py
jiraX-18.0.0.dist-info/METADATA
jiraX-18.0.0.dist-info/WHEEL
jiraX-18.0.0.dist-info/top_level.txt
jiraX-18.0.0.dist-info/RECORD
